topsis/__init__.py
topsis/topsis.py
topsis_rishabh_102203060-1.0.3.dist-info/METADATA
topsis_rishabh_102203060-1.0.3.dist-info/WHEEL
topsis_rishabh_102203060-1.0.3.dist-info/entry_points.txt
topsis_rishabh_102203060-1.0.3.dist-info/top_level.txt
topsis_rishabh_102203060-1.0.3.dist-info/RECORD
